README.rst
flake8_blind_except.py
setup.py
flake8_blind_except.egg-info/PKG-INFO
flake8_blind_except.egg-info/SOURCES.txt
flake8_blind_except.egg-info/dependency_links.txt
flake8_blind_except.egg-info/entry_points.txt
flake8_blind_except.egg-info/not-zip-safe
flake8_blind_except.egg-info/pbr.json
flake8_blind_except.egg-info/requires.txt
flake8_blind_except.egg-info/top_level.txt