Metadata-Version: 1.0
Name: flake8-blind-except
Version: 0.1.1
Summary: A flake8 extension that checks for blind except: statements
Home-page: https://github.com/elijahandrews/flake8-blind-except
Author: Elijah Andrews
Author-email: elijahcandrews@gmail.com
License: MIT
Keywords: flake8 except exception
Platform: UNKNOWN
